django_view_acl-0.1.dist-info/DESCRIPTION.rst
django_view_acl-0.1.dist-info/METADATA
django_view_acl-0.1.dist-info/metadata.json
django_view_acl-0.1.dist-info/RECORD
django_view_acl-0.1.dist-info/top_level.txt
django_view_acl-0.1.dist-info/WHEEL
view_acl/admin.py
view_acl/constants.py
view_acl/middleware.py
view_acl/models.py
view_acl/tests.py
view_acl/utils.py
view_acl/views.py
view_acl/__init__.py
view_acl/migrations/__init__.py
