Metadata-Version: 2.0
Name: django-view-acl
Version: 0.1
Summary: Views ACL plugin is a Django app to provide method for automatic permissions generation based on urlpatterns in urls.py
Home-page: https://github.com/Perfectial/django-view-acl
Author: UNKNOWN
Author-email: UNKNOWN
License: Apache License
Platform: UNKNOWN
Classifier: Environment :: Web Environment
Classifier: Framework :: Django
Classifier: Intended Audience :: Developers
Classifier: License :: OSI Approved :: Apache Software License
Classifier: Operating System :: OS Independent
Classifier: Programming Language :: Python
Classifier: Programming Language :: Python :: 3
Classifier: Topic :: Internet :: WWW/HTTP
Classifier: Topic :: Internet :: WWW/HTTP :: Dynamic Content
